Metadata-Version: 1.1
Name: rainbow-logging-handler
Version: 2.2.1
Summary: Ultimate Python colorized logger with user-custom color
Home-page: https://github.com/laysakura/rainbow_logging_handler
Author: Mikko Ohtamaa, Sho Nakatani
Author-email: mikko@opensourcehacker.com, lay.sakura@gmail.com
License: LICENSE.txt
Platform: UNKNOWN
Classifier: Programming Language :: Python
Classifier: Development Status :: 5 - Production/Stable
Classifier: License :: Public Domain
Classifier: Programming Language :: Python :: 2.6
Classifier: Programming Language :: Python :: 2.7
Classifier: Programming Language :: Python :: 3.2
Classifier: Programming Language :: Python :: 3.3
Classifier: Programming Language :: Python :: Implementation :: PyPy
Classifier: Operating System :: POSIX :: Linux
Classifier: Operating System :: POSIX :: BSD
Classifier: Operating System :: Unix
Classifier: Operating System :: MacOS
Classifier: Operating System :: Microsoft :: Windows
Classifier: Intended Audience :: Developers
Classifier: Topic :: Software Development :: Debuggers
Classifier: Topic :: System :: Logging
Classifier: Topic :: Terminals
Classifier: Topic :: Utilities
